dev_fenics_dijitso-2019.2.1.data/data/share/man/man1/dijitso.1.gz
dijitso/__init__.py
dijitso/__main__.py
dijitso/build.py
dijitso/cache.py
dijitso/cmdline.py
dijitso/jit.py
dijitso/log.py
dijitso/mpi.py
dijitso/params.py
dijitso/signatures.py
dijitso/str.py
dijitso/system.py
dev_fenics_dijitso-2019.2.1.dist-info/COPYING
dev_fenics_dijitso-2019.2.1.dist-info/COPYING.LESSER
dev_fenics_dijitso-2019.2.1.dist-info/METADATA
dev_fenics_dijitso-2019.2.1.dist-info/WHEEL
dev_fenics_dijitso-2019.2.1.dist-info/entry_points.txt
dev_fenics_dijitso-2019.2.1.dist-info/top_level.txt
dev_fenics_dijitso-2019.2.1.dist-info/RECORD
