Metadata-Version: 2.1
Name: dev-fenics-dijitso
Version: 2019.2.1
Summary: Distributed just-in-time building of shared libraries
Home-page: https://bitbucket.org/fenics-project/dijitso/
Download-URL: https://bitbucket.org/fenics-project/dijitso/downloads/dijitso-2019.2.1.tar.gz
Author: Martin Sandve Alnæs
Author-email: martinal@simula.no
License: UNKNOWN
Platform: UNKNOWN
Classifier: Development Status :: 5 - Production/Stable
Classifier: Intended Audience :: Developers
Classifier: Intended Audience :: Science/Research
Classifier: License :: OSI Approved :: GNU Lesser General Public License v3 or later (LGPLv3+)
Classifier: Operating System :: POSIX
Classifier: Operating System :: POSIX :: Linux
Classifier: Operating System :: MacOS :: MacOS X
Classifier: Operating System :: Microsoft :: Windows
Classifier: Programming Language :: Python
Classifier: Programming Language :: Python :: 3
Classifier: Programming Language :: Python :: 3.5
Classifier: Programming Language :: Python :: 3.6
Classifier: Topic :: Scientific/Engineering :: Mathematics
Classifier: Topic :: Software Development :: Libraries :: Python Modules
License-File: COPYING
License-File: COPYING.LESSER
Requires-Dist: numpy
